fast_string_match-0.1.5.dist-info/METADATA
fast_string_match-0.1.5.dist-info/WHEEL
fast_string_match/__init__.py
fast_string_match/fast_string_match.cpython-39-x86_64-linux-gnu.so
fast_string_match-0.1.5.dist-info/RECORD
