Metadata-Version: 2.3
Name: fast_string_match
Version: 0.1.5
Classifier: Programming Language :: Rust
Classifier: Programming Language :: Python :: Implementation :: CPython
Classifier: Programming Language :: Python :: Implementation :: PyPy
Summary: fast string matching built in rust for python, use would be 
Requires-Python: >=3.8
